xyrha_flush/__init__.py
xyrha_flush/example.py
xyrha_flush/py.typed
xyrha_flush-0.1.0.dist-info/AUTHORS.md
xyrha_flush-0.1.0.dist-info/LICENSE.txt
xyrha_flush-0.1.0.dist-info/METADATA
xyrha_flush-0.1.0.dist-info/WHEEL
xyrha_flush-0.1.0.dist-info/top_level.txt
xyrha_flush-0.1.0.dist-info/RECORD
