Metadata-Version: 2.1
Name: xyrha-flush
Version: 0.1.0
Summary: A tool runner for C++ development.
Home-page: https://github.com/xyrha/xyrha-flush
Author: DS422
Author-email: 119532762+DS422@users.noreply.github.com
License: MIT
Requires-Python: >=3.12
License-File: LICENSE.txt
License-File: AUTHORS.md
Requires-Dist: importlib-metadata
Provides-Extra: build
Requires-Dist: build[virtualenv] ; extra == 'build'
Provides-Extra: dev
Requires-Dist: tox ; extra == 'dev'
Requires-Dist: black ; extra == 'dev'
Requires-Dist: ruff ; extra == 'dev'
Requires-Dist: mypy ; extra == 'dev'
Requires-Dist: pylint ; extra == 'dev'
Requires-Dist: pytest ; extra == 'dev'
Requires-Dist: pytest-randomly ; extra == 'dev'
Requires-Dist: pytest-cov ; extra == 'dev'
Requires-Dist: sphinx ; extra == 'dev'
Requires-Dist: sphinx-material ; extra == 'dev'
Requires-Dist: myst-parser ; extra == 'dev'
Requires-Dist: build[virtualenv] ; extra == 'dev'
Provides-Extra: doc
Requires-Dist: sphinx ; extra == 'doc'
Requires-Dist: sphinx-material ; extra == 'doc'
Requires-Dist: myst-parser ; extra == 'doc'
Provides-Extra: lint
Requires-Dist: black ; extra == 'lint'
Requires-Dist: ruff ; extra == 'lint'
Requires-Dist: mypy ; extra == 'lint'
Requires-Dist: pylint ; extra == 'lint'
Requires-Dist: pytest ; extra == 'lint'
Provides-Extra: test
Requires-Dist: pytest ; extra == 'test'
Requires-Dist: pytest-randomly ; extra == 'test'
Requires-Dist: pytest-cov ; extra == 'test'
